pynex/__init__.py
pynex/best_font.py
pynex/checkbox.py
pynex/checkbox_animated.py
pynex/child_collector.py
pynex/cursor_lib.py
pynex/custom_object.py
pynex/flags.py
pynex/fps_clock.py
pynex/hello_msg.py
pynex/horizontal_slider.py
pynex/image.py
pynex/label.py
pynex/main_frame.py
pynex/progress_bar.py
pynex/simple_color_fade.py
pynex/simple_line_edit.py
pynex/timer.py
pynex/utils.py
pynex/vertical_slider.py
pynex/win_animated_button.py
pynex/win_button.py
pynex-0.1.2.dist-info/LICENSE
pynex-0.1.2.dist-info/METADATA
pynex-0.1.2.dist-info/WHEEL
pynex-0.1.2.dist-info/top_level.txt
pynex-0.1.2.dist-info/RECORD
