Metadata-Version: 2.1
Name: pynex
Version: 0.1.2
Summary: PyGame-based GUI Library.
Home-page: https://github.com/Pixelsuft/pynex
Author: Pixelsuft
License: MIT
Project-URL: Readme, https://github.com/Pixelsuft/pynex/blob/main/README.MD
Project-URL: Example, https://github.com/Pixelsuft/pynex/blob/main/main.py
Project-URL: Issue tracker, https://github.com/Pixelsuft/pynex/issues
Keywords: pynex
Platform: UNKNOWN
Classifier: License :: OSI Approved :: MIT License
Classifier: Programming Language :: Python :: 3.6
Classifier: Programming Language :: Python :: 3.7
Classifier: Programming Language :: Python :: 3.8
Classifier: Programming Language :: Python :: 3.9
Requires-Python: >=3.6
License-File: LICENSE
Requires-Dist: pygame
Requires-Dist: Pillow
